mem679_snake/__init__.py
mem679_snake/config.py
mem679_snake/food.py
mem679_snake/game.py
mem679_snake/main.py
mem679_snake/snake.py
MEM679_snake-0.1.3.dist-info/LICENSE.txt
MEM679_snake-0.1.3.dist-info/METADATA
MEM679_snake-0.1.3.dist-info/WHEEL
MEM679_snake-0.1.3.dist-info/entry_points.txt
MEM679_snake-0.1.3.dist-info/top_level.txt
MEM679_snake-0.1.3.dist-info/RECORD
