Metadata-Version: 2.1
Name: MEM679-snake
Version: 0.1.3
Summary: Add a short description here!
Home-page: https://github.com/pyscaffold/pyscaffold/
Author: jagar2
Author-email: jca92@drexel.edu
License: MIT
Project-URL: Documentation, https://pyscaffold.org/
Platform: any
Classifier: Development Status :: 4 - Beta
Classifier: Programming Language :: Python
License-File: LICENSE.txt
Requires-Dist: pygame
Requires-Dist: importlib-metadata ; python_version < "3.8"
Provides-Extra: testing
Requires-Dist: setuptools ; extra == 'testing'
Requires-Dist: pytest ; extra == 'testing'
Requires-Dist: pytest-cov ; extra == 'testing'
